{
  "version": 1,
  "license": "CC-BY-SA-3.0",
  "copyright": "Taken from shiptest-ss13 at https://github.com/shiptest-ss13/Shiptest/blob/c8cdc0bb44cdb96cc1562666bc6df2fbdd71c42d/icons/obj/wallmounts/apc.dmi, https://github.com/shiptest-ss13/Shiptest/blob/c8cdc0bb44cdb96cc1562666bc6df2fbdd71c42d/icons/obj/wallmounts/wallframe_items.dmi, modified by github noctyrnal",
  "size": {
    "x": 32,
    "y": 32
  },
  "states": [
    {
      "name": "base",
      "directions": 4
    },
	{
      "name": "static"
    },
    {
      "name": "broken",
      "directions": 4
    },
    {
      "name": "frame",
      "directions": 4
    },
    {
      "name": "panel",
      "directions": 4
    },
    {
      "name": "lock0-locked",
      "directions": 4
    },
    {
      "name": "lock1-locked",
      "directions": 4
    },
    {
      "name": "display-lack",
      "directions": 4
    },
    {
      "name": "display-charging",
      "directions": 4
    },
    {
      "name": "display-full",
      "directions": 4
    },
    {
      "name": "display-remote",
      "directions": 4
    },
    {
      "name": "emag-unlit",
      "directions": 4
    },
    {
      "name": "sparks-unlit",
      "delays": [
        [
          0.1,
          0.1,
          0.1,
          0.1,
          0.1,
          0.1
        ]
      ]
    }
  ]
}
